predictnow/__init__.py
predictnow/find_files_with_specific_extensions.py
predictnow/notifier.py
predictnow/pdapi.py
predictnow/predict_result.py
predictnow/training_result.py
predictnow_client-0.0.9.dist-info/LICENSE
predictnow_client-0.0.9.dist-info/METADATA
predictnow_client-0.0.9.dist-info/WHEEL
predictnow_client-0.0.9.dist-info/top_level.txt
predictnow_client-0.0.9.dist-info/RECORD
